bin/__init__.py
bin/blame.py
bin/cli.py
clacky_stats-0.1.4.dist-info/LICENSE
clacky_stats-0.1.4.dist-info/METADATA
clacky_stats-0.1.4.dist-info/WHEEL
clacky_stats-0.1.4.dist-info/entry_points.txt
clacky_stats-0.1.4.dist-info/RECORD
