Metadata-Version: 2.3
Name: clacky-stats
Version: 0.1.4
Summary: Code contribution statistics tool for Clacky AI projects
License: MIT
Author: ClackyAI
Author-email: contact@clacky.ai
Requires-Python: >=3.8
Classifier: Development Status :: 4 - Beta
Classifier: Environment :: Console
Classifier: Intended Audience :: Developers
Classifier: License :: OSI Approved :: MIT License
Classifier: Operating System :: OS Independent
Classifier: Programming Language :: Python :: 3
Classifier: Programming Language :: Python :: 3.8
Classifier: Programming Language :: Python :: 3.9
Classifier: Programming Language :: Python :: 3.10
Classifier: Programming Language :: Python :: 3.11
Classifier: Programming Language :: Python :: 3.12
Classifier: Programming Language :: Python :: 3.13
Classifier: Topic :: Software Development :: Version Control :: Git
Requires-Dist: codespell
Requires-Dist: cogapp
Requires-Dist: imgcat
Requires-Dist: matplotlib
Requires-Dist: pandas
Requires-Dist: pyyaml
Requires-Dist: rich
Requires-Dist: semver
Requires-Dist: tqdm
Requires-Dist: typer
Requires-Dist: uv
Project-URL: Documentation, https://github.com/clacky-ai/clacky-stats#readme
Project-URL: Homepage, https://github.com/clacky-ai/clacky-stats
Project-URL: Repository, https://github.com/clacky-ai/clacky-stats.git
